utiltools/__init__.py
utiltools/events.py
utiltools/func_utils.py
utiltools/maybe.py
utiltools/miscutils.py
utiltools/perm.py
utiltools/phone_finder.py
utiltools/procutils.py
utiltools/scraper_utils.py
utiltools/secpass.py
utiltools/shellutils.py
utiltools/test_perm.py
utiltools/tests.py
utiltools/timeutils.py
utiltools/work_queue.py
utiltools/dbutils/UserPermissions.py
utiltools/dbutils/__init__.py
utiltools/dbutils/account_manager.py
utiltools/dbutils/account_manager_sqlite.py
utiltools/dbutils/alc.py
utiltools/dbutils/alc_conf.py
utiltools/dbutils/atomicid.py
utiltools/dbutils/dbdict.py
utiltools/dbutils/dbhelpers.py
utiltools/dbutils/secpassdb.py
utiltools/dbutils/sqlite_wrapper.py
utiltools-0.0.5.dist-info/METADATA
utiltools-0.0.5.dist-info/RECORD
utiltools-0.0.5.dist-info/WHEEL
utiltools-0.0.5.dist-info/top_level.txt
