Metadata-Version: 2.1
Name: utiltools
Version: 0.0.5
Summary: Misc tools
Home-page: UNKNOWN
Author: Konstantin Kowalski
Author-email: kostelkow@gmail.com
License: UNKNOWN
Platform: UNKNOWN
Requires-Dist: gunicorn
Requires-Dist: user-agents
Requires-Dist: sh
Requires-Dist: Flask
Requires-Dist: Flask-Limiter
Requires-Dist: Flask-Session
